prompt_injection_bench/__init__.py
prompt_injection_bench/azure_openai_async_prompt_guard.py
prompt_injection_bench/azure_openai_prompt_guard.py
prompt_injection_bench/gemini_async_prompt_guard.py
prompt_injection_bench/gemini_prompt_guard.py
prompt_injection_bench/index.html
prompt_injection_bench/openai_async_prompt_guard.py
prompt_injection_bench/openai_prompt_guard.py
prompt_injection_bench/server.py
prompt_injection_bench/static/eye_line_art.png
prompt_injection_bench/static/inside_line_art.png
prompt_injection_bench/static/script.js
prompt_injection_bench/static/style.css
prompt_injection_bench-0.1.13.dist-info/LICENSE
prompt_injection_bench-0.1.13.dist-info/METADATA
prompt_injection_bench-0.1.13.dist-info/WHEEL
prompt_injection_bench-0.1.13.dist-info/RECORD
