Metadata-Version: 2.1
Name: prompt-injection-bench
Version: 0.1.13
Summary: Package to test Prompt Injection Against OpenAI's ChatGPT, Google's Gemini and Azure Open AI
License: Apache 2.0
Author: BenderScript
Author-email: 6779302+BenderScript@users.noreply.github.com
Requires-Python: >=3.11,<4.0
Classifier: License :: Other/Proprietary License
Classifier: Programming Language :: Python :: 3
Classifier: Programming Language :: Python :: 3.11
Classifier: Programming Language :: Python :: 3.12
Requires-Dist: datasets (==2.17.0)
Requires-Dist: fastapi (>=0.109.2,<0.110.0)
Requires-Dist: google-generativeai (==0.3.2)
Requires-Dist: httpx (>=0.25.2,<0.26.0)
Requires-Dist: openai (==1.13.3)
Requires-Dist: pydantic (==2.6.1)
Requires-Dist: python-dotenv (==1.0.1)
Requires-Dist: requests (>=2.31.0,<3.0.0)
Requires-Dist: uvicorn (>=0.25.0,<0.26.0)
Requires-Dist: websockets (>=12.0,<13.0)
